warpzone/__init__.py
warpzone/servicebus/__init__.py
warpzone/servicebus/data.py
warpzone/tablestorage/__init__.py
warpzone/tablestorage/client.py
warpzone-0.0.1.dist-info/WHEEL
warpzone-0.0.1.dist-info/METADATA
warpzone-0.0.1.dist-info/RECORD
