Metadata-Version: 2.1
Name: warpzone
Version: 0.0.1
Summary: The main objective of this package is to centralize logic used to interact with Azure Functions, Azure Service Bus and Azure Table Storage
Author: Anders Launer Baek-Petersen
Author-email: alp@energinet.dk
Requires-Python: >=3.9,<4.0
Classifier: Programming Language :: Python :: 3
Classifier: Programming Language :: Python :: 3.10
Classifier: Programming Language :: Python :: 3.9
Requires-Dist: azure-data-tables (>=12.4.0,<13.0.0)
Requires-Dist: azure-functions (>=1.11.2,<2.0.0)
Requires-Dist: pandas (>=1.4.3,<2.0.0)
Requires-Dist: pyarrow (>=9.0.0,<10.0.0)
